RH23003UNO/__init__.py
RH23003UNO/biseccion.py
RH23003UNO/crammer.py
RH23003UNO/descomposicion_lu.py
RH23003UNO/gauss.py
RH23003UNO/gauss_jordan.py
RH23003UNO/gauss_seidel.py
RH23003UNO/jacobi.py
rh23003uno-0.1.1.dist-info/licenses/LICENSE.txt
rh23003uno-0.1.1.dist-info/METADATA
rh23003uno-0.1.1.dist-info/WHEEL
rh23003uno-0.1.1.dist-info/top_level.txt
rh23003uno-0.1.1.dist-info/RECORD
