Metadata-Version: 2.4
Name: RH23003UNO
Version: 0.1.1
Summary: Este paquete contiene métodos numéricos en Python
Author: Isai Hidalgo
Author-email: isai.arh18@gmail.com
License: MIT
Keywords: métodos numéricos,python
Classifier: Development Status :: 5 - Production/Stable
Classifier: Intended Audience :: Education
Classifier: Operating System :: Microsoft :: Windows :: Windows 10
Classifier: License :: OSI Approved :: MIT License
Classifier: Programming Language :: Python :: 3
License-File: LICENSE.txt
Requires-Dist: numpy
Dynamic: author
Dynamic: author-email
Dynamic: classifier
Dynamic: description
Dynamic: description-content-type
Dynamic: keywords
Dynamic: license
Dynamic: license-file
Dynamic: requires-dist
Dynamic: summary
